kved_finder/__init__.py
kved_finder/kved_finder.py
kved_finder-2.6.dist-info/METADATA
kved_finder-2.6.dist-info/WHEEL
kved_finder-2.6.dist-info/top_level.txt
kved_finder-2.6.dist-info/RECORD
