Metadata-Version: 2.1
Name: kved-finder
Version: 2.6
Summary: A package for finding kved tree
Home-page: https://github.com/elem3ntary/kved_finder
Author: elem3ntary
Author-email: impr0digg@gmai.com
License: UNKNOWN
Platform: UNKNOWN
Classifier: Programming Language :: Python :: 3
Classifier: License :: OSI Approved :: MIT License
Classifier: Operating System :: OS Independent
Requires-Python: >=3.7
Requires-Dist: requests
